latents/__init__.py
latents-0.0.1.dist-info/LICENSE
latents-0.0.1.dist-info/METADATA
latents-0.0.1.dist-info/WHEEL
latents-0.0.1.dist-info/top_level.txt
latents-0.0.1.dist-info/RECORD
