Metadata-Version: 2.1
Name: latents
Version: 0.0.1
Summary: A toolkit for latent variable modeling and dimensionality reduction
Author-email: Evren Gokcen <egokcen@cmu.edu>
License: MIT License
Keywords: latents,latent variables,latent variable model,dimensionality reduction,machine learning,unsupervised learning
Classifier: Programming Language :: Python :: 3
Classifier: License :: OSI Approved :: MIT License
Classifier: Operating System :: OS Independent
Classifier: Intended Audience :: Science/Research
Classifier: Topic :: Scientific/Engineering
Requires-Python: >=3.10
License-File: LICENSE
Provides-Extra: dev
Provides-Extra: doc
